test/__init__.py
test/test_ban_response.py
test/test_base_quote_response.py
test/test_block_api.py
test/test_block_response.py
test/test_block_response_header.py
test/test_block_response_header_version.py
test/test_block_response_id.py
test/test_block_response_id_parts.py
test/test_block_tx.py
test/test_block_tx_result.py
test/test_cacao_pool_api.py
test/test_cacao_pool_response.py
test/test_cacao_pool_response_providers.py
test/test_cacao_pool_response_reserve.py
test/test_cacao_provider.py
test/test_cacao_provider_response.py
test/test_cacao_providers_response.py
test/test_chain_height.py
test/test_coin.py
test/test_constants_response.py
test/test_health_api.py
test/test_inbound_address.py
test/test_inbound_addresses_response.py
test/test_inbound_confirmation_counted_stage.py
test/test_inbound_finalised_stage.py
test/test_inbound_observed_stage.py
test/test_invariant_response.py
test/test_invariants_api.py
test/test_invariants_response.py
test/test_keygen.py
test/test_keygen_block.py
test/test_keygen_metric.py
test/test_keygen_metrics_response.py
test/test_keygen_response.py
test/test_keysign_info.py
test/test_keysign_metrics.py
test/test_keysign_response.py
test/test_last_block.py
test/test_last_block_response.py
test/test_liquidity_provider.py
test/test_liquidity_provider_response.py
test/test_liquidity_provider_summary.py
test/test_liquidity_providers_api.py
test/test_liquidity_providers_response.py
test/test_lp_bonded_node.py
test/test_mayaname.py
test/test_mayaname1.py
test/test_mayaname_alias.py
test/test_mayaname_response.py
test/test_mayaname_subaffiliate.py
test/test_mayanames_api.py
test/test_metrics_response.py
test/test_mimir_api.py
test/test_mimir_nodes_response.py
test/test_mimir_response.py
test/test_mimir_vote.py
test/test_msg_swap.py
test/test_network_api.py
test/test_network_response.py
test/test_node.py
test/test_node_bond_provider.py
test/test_node_bond_providers.py
test/test_node_jail.py
test/test_node_keygen_metric.py
xchainpy2_mayanode-1.118.0.dist-info/LICENSE
xchainpy2_mayanode-1.118.0.dist-info/METADATA
xchainpy2_mayanode-1.118.0.dist-info/WHEEL
xchainpy2_mayanode-1.118.0.dist-info/top_level.txt
xchainpy2_mayanode-1.118.0.dist-info/RECORD
