Metadata-Version: 2.2
Name: xchainpy2-mayanode
Version: 1.118.0
Summary: Mayanode API
Home-page: 
Author-email: devs@mayachain.org
Keywords: Swagger,Mayanode API
License-File: LICENSE
Requires-Dist: urllib3>=1.15
Requires-Dist: six>=1.10
Requires-Dist: certifi
Requires-Dist: python-dateutil
Requires-Dist: aiohttp
Dynamic: author-email
Dynamic: description
Dynamic: description-content-type
Dynamic: keywords
Dynamic: requires-dist
Dynamic: summary
